secdoc/__init__.py
secdoc/main.py
secdoc-0.1.2.dist-info/METADATA
secdoc-0.1.2.dist-info/WHEEL
secdoc-0.1.2.dist-info/licenses/LICENSE
secdoc-0.1.2.dist-info/RECORD
